setup.py
django_encrypted_settings.egg-info/PKG-INFO
django_encrypted_settings.egg-info/SOURCES.txt
django_encrypted_settings.egg-info/dependency_links.txt
django_encrypted_settings.egg-info/requires.txt
django_encrypted_settings.egg-info/top_level.txt
encrypted_settings/__init__.py
encrypted_settings/config.py
encrypted_settings/crypter.py
encrypted_settings/management/__init__.py
encrypted_settings/management/commands/__init__.py
encrypted_settings/management/commands/_base.py
encrypted_settings/management/commands/decrypt.py
encrypted_settings/management/commands/encrypt.py