Metadata-Version: 1.1
Name: django-encrypted-settings
Version: 0.1.0
Summary: Thin wrapper around Python keyczar bindings which allows you to manage and use encrypted settings in your Django app.
Home-page: https://github.com/Kami/django-encrypted-settings
Author: Tomaz Muraus
Author-email: tomaz@tomaz.me
License: UNKNOWN
Platform: Any
Classifier: Development Status :: 2 - Pre-Alpha
Classifier: License :: OSI Approved :: Apache Software License
Classifier: Programming Language :: Python
Classifier: Programming Language :: Python :: 2.6
Classifier: Programming Language :: Python :: 2.7
Classifier: Programming Language :: Python :: Implementation :: PyPy
Classifier: Environment :: Console
